LICENSE.txt
Readme.md
mfranceschi_minesweeper/__init__.py
mfranceschi_minesweeper/controller/__init__.py
mfranceschi_minesweeper/controller/controller.py
mfranceschi_minesweeper/controller/controller_impl.py
mfranceschi_minesweeper/controller/game.py
mfranceschi_minesweeper/main.py
mfranceschi_minesweeper/model/__init__.py
mfranceschi_minesweeper/model/cell.py
mfranceschi_minesweeper/model/dummy_grid.py
mfranceschi_minesweeper/model/fill_grid.py
mfranceschi_minesweeper/model/grid.py
mfranceschi_minesweeper/model/grid_impl_with_python_list.py
mfranceschi_minesweeper/model/gridmanager.py
mfranceschi_minesweeper/utils/__init__.py
mfranceschi_minesweeper/utils/action_on_close.py
mfranceschi_minesweeper/utils/decorators.py
mfranceschi_minesweeper/utils/filepaths.py
mfranceschi_minesweeper/utils/point2d.py
mfranceschi_minesweeper/view/__init__.py
mfranceschi_minesweeper/view/cell_button_configurator.py
mfranceschi_minesweeper/view/cell_view.py
mfranceschi_minesweeper/view/controls.py
mfranceschi_minesweeper/view/grid_view.py
mfranceschi_minesweeper/view/gui.py
mfranceschi_minesweeper/view/gui_impl.py
mfranceschi_minesweeper/view/icons.py
requirements.txt
mfranceschi_minesweeper-0.2.3.dist-info/entry_points.txt
mfranceschi_minesweeper-0.2.3.dist-info/LICENSE.txt
mfranceschi_minesweeper-0.2.3.dist-info/WHEEL
mfranceschi_minesweeper-0.2.3.dist-info/METADATA
mfranceschi_minesweeper-0.2.3.dist-info/RECORD
