Metadata-Version: 2.1
Name: mfranceschi-minesweeper
Version: 0.2.3
Summary: A cool minesweeper
Home-page: https://github.com/mfranceschi/Minesweeper/
License: MIT
Author: mfranceschi
Requires-Python: >=3.7,<4.0
Classifier: License :: OSI Approved :: MIT License
Classifier: Operating System :: OS Independent
Classifier: Programming Language :: Python :: 3
Classifier: Programming Language :: Python :: 3 :: Only
Classifier: Programming Language :: Python :: 3.7
Classifier: Programming Language :: Python :: 3.8
Classifier: Programming Language :: Python :: 3.9
Classifier: Topic :: Games/Entertainment
Classifier: Topic :: Games/Entertainment :: Arcade
Classifier: Topic :: Games/Entertainment :: Board Games
Requires-Dist: Pillow (>=8.3,<9.0)
Requires-Dist: overrides (>=6.1,<6.2)
Project-URL: Repository, https://github.com/mfranceschi/Minesweeper/
